trackl_client/__init__.py
trackl_client/cli.py
trackl_client-2.1.2.dist-info/WHEEL
trackl_client-2.1.2.dist-info/METADATA
trackl_client-2.1.2.dist-info/RECORD
